pyfeign/__init__.py
pyfeign/config.py
pyfeign/main.py
pyfeign/serializer.py
pyfeign-0.1.2.dist-info/LICENSE
pyfeign-0.1.2.dist-info/WHEEL
pyfeign-0.1.2.dist-info/METADATA
pyfeign-0.1.2.dist-info/RECORD
