Metadata-Version: 2.1
Name: pyfeign
Version: 0.1.2
Summary: Declarative Python HTTP Client, inspired by the OpenFeign java project
Home-page: https://github.com/chriswhite199/pyfeign
License: MIT
Author: Chris White
Author-email: chriswhite199@gmail.com
Requires-Python: >=3.8
Classifier: License :: OSI Approved :: MIT License
Classifier: Programming Language :: Python :: 3
Classifier: Programming Language :: Python :: 3.8
Classifier: Programming Language :: Python :: 3.9
Classifier: Programming Language :: Python :: 3.10
Classifier: Programming Language :: Python :: 3.11
Requires-Dist: requests (>=2.27.1,<3.0.0)
